opencredit/auth/default.py
opencredit/auth/key.py
opencredit/auth/principal.py
opencredit/auth/provider.py
opencredit/auth/transport.py
opencredit/balance.py
opencredit/credit.py
opencredit/db/conn.py
opencredit/db/models.py
opencredit/meter.py
opencredit/server/app.py
opencredit/server/models.py
opencredit/server/router/base.py
opencredit/transaction.py
opencredit-0.1.1.dist-info/LICENSE
opencredit-0.1.1.dist-info/METADATA
opencredit-0.1.1.dist-info/WHEEL
opencredit-0.1.1.dist-info/RECORD
